functiondefextractor/__init__.py
functiondefextractor/__main__.py
functiondefextractor/condition_checker.py
functiondefextractor/core_extractor.py
functiondefextractor/extractor_cmd.py
functiondefextractor/extractor_log.py
functiondefextractor-0.1.2.dist-info/LICENSE.md
functiondefextractor-0.1.2.dist-info/METADATA
functiondefextractor-0.1.2.dist-info/WHEEL
functiondefextractor-0.1.2.dist-info/top_level.txt
functiondefextractor-0.1.2.dist-info/RECORD
