Metadata-Version: 2.1
Name: functiondefextractor
Version: 0.1.2
Summary: Function Definition Extractor
Home-page: https://github.com/philips-software/functiondefextractor
Author: Brijesh
Author-email: brijesh.krishnank@philips.com
License: UNKNOWN
Platform: UNKNOWN
Classifier: Programming Language :: Python :: 3
Classifier: License :: OSI Approved :: MIT License
Classifier: Operating System :: OS Independent
Requires-Python: >=3.7
Requires-Dist: xlrd (==1.2.0)
Requires-Dist: xlsxwriter (==1.2.1)
Requires-Dist: pandas (==1.0.5)
